karthik_vg/main.py
src/main.py
karthik_vg-1.0.0.dist-info/LICENSE.txt
karthik_vg-1.0.0.dist-info/METADATA
karthik_vg-1.0.0.dist-info/WHEEL
karthik_vg-1.0.0.dist-info/top_level.txt
karthik_vg-1.0.0.dist-info/RECORD
