Metadata-Version: 2.1
Name: karthik-vg
Version: 1.0.0
Summary: A Python package to get weather reports for any location.
Home-page: UNKNOWN
Author: karthik_vg
Author-email: karthikvg1998@gmail.com
License: MIT
Platform: UNKNOWN
Classifier: License :: OSI Approved :: MIT License
Classifier: Programming Language :: Python :: 3
Classifier: Programming Language :: Python :: 3.7
